torchjd/__init__.py
torchjd/py.typed
torchjd/aggregation/__init__.py
torchjd/aggregation/_aggregator_bases.py
torchjd/aggregation/_aligned_mtl.py
torchjd/aggregation/_cagrad.py
torchjd/aggregation/_config.py
torchjd/aggregation/_constant.py
torchjd/aggregation/_dualproj.py
torchjd/aggregation/_flattening.py
torchjd/aggregation/_graddrop.py
torchjd/aggregation/_imtl_g.py
torchjd/aggregation/_krum.py
torchjd/aggregation/_mean.py
torchjd/aggregation/_mgda.py
torchjd/aggregation/_nash_mtl.py
torchjd/aggregation/_pcgrad.py
torchjd/aggregation/_random.py
torchjd/aggregation/_sum.py
torchjd/aggregation/_trimmed_mean.py
torchjd/aggregation/_upgrad.py
torchjd/aggregation/_weighting_bases.py
torchjd/aggregation/_utils/__init__.py
torchjd/aggregation/_utils/check_dependencies.py
torchjd/aggregation/_utils/dual_cone.py
torchjd/aggregation/_utils/gramian.py
torchjd/aggregation/_utils/non_differentiable.py
torchjd/aggregation/_utils/pref_vector.py
torchjd/aggregation/_utils/str.py
torchjd/autogram/__init__.py
torchjd/autogram/_edge_registry.py
torchjd/autogram/_engine.py
torchjd/autogram/_gramian_accumulator.py
torchjd/autogram/_gramian_computer.py
torchjd/autogram/_gramian_utils.py
torchjd/autogram/_jacobian_computer.py
torchjd/autogram/_module_hook_manager.py
torchjd/autojac/__init__.py
torchjd/autojac/_backward.py
torchjd/autojac/_mtl_backward.py
torchjd/autojac/_utils.py
torchjd/autojac/_transform/__init__.py
torchjd/autojac/_transform/_accumulate.py
torchjd/autojac/_transform/_aggregate.py
torchjd/autojac/_transform/_base.py
torchjd/autojac/_transform/_diagonalize.py
torchjd/autojac/_transform/_differentiate.py
torchjd/autojac/_transform/_grad.py
torchjd/autojac/_transform/_init.py
torchjd/autojac/_transform/_jac.py
torchjd/autojac/_transform/_materialize.py
torchjd/autojac/_transform/_ordered_set.py
torchjd/autojac/_transform/_select.py
torchjd/autojac/_transform/_stack.py
torchjd-0.8.1.dist-info/METADATA
torchjd-0.8.1.dist-info/WHEEL
torchjd-0.8.1.dist-info/top_level.txt
torchjd-0.8.1.dist-info/RECORD
