Metadata-Version: 2.4
Name: torchjd
Version: 0.8.1
Summary: Library for Jacobian Descent with PyTorch.
Author-email: Valerian Rey <valerian.rey@gmail.com>, Pierre Quinton <pierre.quinton@gmail.com>
License: MIT License
Project-URL: Homepage, https://torchjd.org/
Project-URL: Documentation, https://torchjd.org/
Project-URL: Source, https://github.com/TorchJD/torchjd
Project-URL: Changelog, https://github.com/TorchJD/torchjd/blob/main/CHANGELOG.md
Classifier: Development Status :: 4 - Beta
Classifier: Intended Audience :: Developers
Classifier: Intended Audience :: Science/Research
Classifier: Operating System :: OS Independent
Classifier: Programming Language :: Python
Classifier: Programming Language :: Python :: 3
Classifier: Programming Language :: Python :: 3.10
Classifier: Programming Language :: Python :: 3.11
Classifier: Programming Language :: Python :: 3.12
Classifier: Programming Language :: Python :: 3.13
Classifier: Programming Language :: Python :: 3.14
Classifier: Topic :: Scientific/Engineering
Classifier: Topic :: Scientific/Engineering :: Artificial Intelligence
Requires-Python: >=3.10
Requires-Dist: torch>=2.0.0
Requires-Dist: quadprog!=0.1.10,>=0.1.9
Requires-Dist: numpy>=1.21.0
Requires-Dist: qpsolvers>=1.0.1
Provides-Extra: nash-mtl
Requires-Dist: cvxpy>=1.3.0; extra == "nash-mtl"
Requires-Dist: ecos>=2.0.14; extra == "nash-mtl"
Provides-Extra: cagrad
Requires-Dist: cvxpy>=1.3.0; extra == "cagrad"
Provides-Extra: full
Requires-Dist: cvxpy>=1.3.0; extra == "full"
Requires-Dist: ecos>=2.0.14; extra == "full"
